RedLeader-0.1.5.dist-info/DESCRIPTION.rst
RedLeader-0.1.5.dist-info/METADATA
RedLeader-0.1.5.dist-info/RECORD
RedLeader-0.1.5.dist-info/WHEEL
RedLeader-0.1.5.dist-info/entry_points.txt
RedLeader-0.1.5.dist-info/metadata.json
RedLeader-0.1.5.dist-info/top_level.txt
redleader/__init__.py
redleader/cluster.py
redleader/code_deploy.py
redleader/ec2.py
redleader/exceptions.py
redleader/redleader.py
redleader/util.py
redleader/managers/__init__.py
redleader/managers/codedeploy.py
redleader/resources/__init__.py
redleader/resources/cloudwatch.py
redleader/resources/codedeploy.py
redleader/resources/dynamodb.py
redleader/resources/ec2.py
redleader/resources/iam.py
redleader/resources/permissions.py
redleader/resources/resource.py
redleader/resources/s3.py
redleader/resources/sqs.py
