Metadata-Version: 2.0
Name: RedLeader
Version: 0.1.5
Summary: An automated EC2 & ECS deployment platform
Home-page: UNKNOWN
Author: Morgan McDermott
Author-email: morganmcdermott@gmail.com
License: UNKNOWN
Platform: UNKNOWN
Classifier: Development Status :: 2 - Pre-Alpha
Classifier: Intended Audience :: Developers
Classifier: Natural Language :: English
Classifier: License :: OSI Approved :: MIT License
Classifier: Programming Language :: Python :: 3
Classifier: Programming Language :: Python :: 3.3
Classifier: Programming Language :: Python :: 3.4
Classifier: Programming Language :: Python :: 3.5
